README.md
setup.cfg
setup.py
scikitsampledistribution/Binomialdistribution.py
scikitsampledistribution/Gaussiandistribution.py
scikitsampledistribution/Generaldistribution.py
scikitsampledistribution/__init__.py
scikitsampledistribution.egg-info/PKG-INFO
scikitsampledistribution.egg-info/SOURCES.txt
scikitsampledistribution.egg-info/dependency_links.txt
scikitsampledistribution.egg-info/not-zip-safe
scikitsampledistribution.egg-info/top_level.txt